package_creation_tutorial/__init__.py
package_creation_tutorial/main.py
package_creation_tutorial/string_ops.py
session_1_python_package-0.2.0.dist-info/LICENSE
session_1_python_package-0.2.0.dist-info/METADATA
session_1_python_package-0.2.0.dist-info/WHEEL
session_1_python_package-0.2.0.dist-info/RECORD
