Metadata-Version: 2.3
Name: SESSION-1-PYTHON-PACKAGE
Version: 0.2.0
Summary: 
Author: Mehyar Mlaweh
Author-email: mehyarmlaweh0@gmail.com
Requires-Python: >=3.11
Classifier: Programming Language :: Python :: 3
Classifier: Programming Language :: Python :: 3.11
Classifier: Programming Language :: Python :: 3.12
Classifier: Programming Language :: Python :: 3.13
Requires-Dist: pre-commit (>=4.0.1,<5.0.0)
Requires-Dist: pytest (>=8.3.4,<9.0.0)
Requires-Dist: pytest-cov (>=6.0.0,<7.0.0)
Requires-Dist: ruff (>=0.9.2,<0.10.0)
Requires-Dist: sortedcontainers (>=2.4.0,<3.0.0)
Requires-Dist: sphinx (>=8.1.3,<9.0.0)
Requires-Dist: sphinx-rtd-theme (>=3.0.2,<4.0.0)
